setup.py
tn_2010/__init__.py
tn_2010/tn_2010.py
tn_test_lib.egg-info/PKG-INFO
tn_test_lib.egg-info/SOURCES.txt
tn_test_lib.egg-info/dependency_links.txt
tn_test_lib.egg-info/not-zip-safe
tn_test_lib.egg-info/top_level.txt