Metadata-Version: 2.1
Name: tn-test-lib
Version: 0.27
Summary: Test for own library
Home-page: UNKNOWN
Author: DA
License: UNKNOWN
Platform: UNKNOWN
